maude/__init__.py
maude/_maude.so
maude/file.maude
maude/libmaude.dylib
maude/linear.maude
maude/machine-int.maude
maude/metaInterpreter.maude
maude/model-checker.maude
maude/prelude.maude
maude/process.maude
maude/smt.maude
maude/socket.maude
maude/term-order.maude
maude/time.maude
maude-1.5.0.dist-info/METADATA
maude-1.5.0.dist-info/WHEEL
maude-1.5.0.dist-info/licenses/LICENSE
maude-1.5.0.dist-info/RECORD
