Metadata-Version: 2.1
Name: maude
Version: 1.5.0
Summary: Python bindings for Maude
Author-Email: ningit <ningit@users.noreply.github.com>
License: GPLv2
Classifier: Intended Audience :: Science/Research
Classifier: Programming Language :: Python
Classifier: Programming Language :: Python :: 3
Classifier: Topic :: Scientific/Engineering
Classifier: Operating System :: OS Independent
Project-URL: Homepage, https://github.com/fadoss/maude-bindings
Project-URL: Bug tracker, https://github.com/fadoss/maude-bindings/issues
Project-URL: Documentation, https://fadoss.github.io/maude-bindings
Project-URL: Source code, https://github.com/fadoss/maude-bindings
